cryptool/__init__.py
cryptool/run_gui.py
cryptool/cli/main.py
cryptool/core/__init__.py
cryptool/core/app.py
cryptool/core/asymmetric.py
cryptool/core/db_config.py
cryptool/core/fernet.py
cryptool/core/file_handler.py
cryptool/core/hashing.py
cryptool/core/hybrid.py
cryptool/core/key_management.py
cryptool/core/key_rotation.py
cryptool/core/symmetric.py
cryptool/gui/main.py
cryptool/gui/main_window.py
cryptool/utils/config_validator.py
cryptool/utils/db_init.py
cryptool/utils/secure_storage.py
cryptool/utils/setup_db.py
huawuque_cryptool-0.2.2.dist-info/licenses/LICENSE
huawuque_cryptool-0.2.2.dist-info/METADATA
huawuque_cryptool-0.2.2.dist-info/WHEEL
huawuque_cryptool-0.2.2.dist-info/entry_points.txt
huawuque_cryptool-0.2.2.dist-info/top_level.txt
huawuque_cryptool-0.2.2.dist-info/RECORD
