Metadata-Version: 2.4
Name: huawuque-cryptool
Version: 0.2.2
Summary: 一个具有GUI界面的加密工具，支持AES、RSA和混合加密
Home-page: https://github.com/hwq/cryptool
Author: hwq
Author-email: hwq@example.com
License: MIT
Project-URL: Bug Tracker, https://github.com/hwq/cryptool/issues
Project-URL: Documentation, https://github.com/hwq/cryptool/wiki
Project-URL: Source Code, https://github.com/hwq/cryptool
Keywords: encryption,cryptography,security,gui,aes,rsa
Classifier: Development Status :: 4 - Beta
Classifier: Intended Audience :: End Users/Desktop
Classifier: Topic :: Security :: Cryptography
Classifier: Programming Language :: Python :: 3
Classifier: Programming Language :: Python :: 3.8
Classifier: Programming Language :: Python :: 3.9
Classifier: Programming Language :: Python :: 3.10
Classifier: Programming Language :: Python :: 3.11
Classifier: Programming Language :: Python :: 3.7
Classifier: License :: OSI Approved :: MIT License
Classifier: Operating System :: OS Independent
Classifier: Environment :: X11 Applications :: Qt
Requires-Python: >=3.8
License-File: LICENSE
Requires-Dist: pycryptodome>=3.9.0
Requires-Dist: python-dotenv>=0.19.0
Requires-Dist: cryptography>=41.0.0
Requires-Dist: mysql-connector-python>=8.0.0
Requires-Dist: psutil>=5.9.0
Requires-Dist: tkinter
Dynamic: author
Dynamic: author-email
Dynamic: classifier
Dynamic: description
Dynamic: description-content-type
Dynamic: home-page
Dynamic: keywords
Dynamic: license
Dynamic: license-file
Dynamic: project-url
Dynamic: requires-dist
Dynamic: requires-python
Dynamic: summary
